dbjobq/__init__.py
dbjobq/models.py
dbjobq/queue.py
dbjobq/worker.py
dbjobq/storage/__init__.py
dbjobq/storage/base.py
dbjobq/storage/dynamo_storage.py
dbjobq/storage/mongo_storage.py
dbjobq/storage/redis_storage.py
dbjobq/storage/sqlalchemy_storage.py
dbjobq-0.1.0.dist-info/METADATA
dbjobq-0.1.0.dist-info/WHEEL
dbjobq-0.1.0.dist-info/RECORD
