Metadata-Version: 2.4
Name: dbjobq
Version: 0.1.0
Summary: A very simple async job queue with a database
Author-email: Scott Caratozzolo <scott@caratozzolo.dev>
Keywords: async,background,database,job,queue
Classifier: Development Status :: 4 - Beta
Classifier: Intended Audience :: Developers
Classifier: Programming Language :: Python :: 3
Requires-Python: <3.14,>=3.9
Requires-Dist: croniter>=5.0.1
Provides-Extra: all
Requires-Dist: aioboto3>=13.3.0; extra == 'all'
Requires-Dist: aioodbc>=0.5.0; extra == 'all'
Requires-Dist: aiosqlite>=0.20.0; extra == 'all'
Requires-Dist: asyncpg>=0.30.0; extra == 'all'
Requires-Dist: boto3>=1.35.3; extra == 'all'
Requires-Dist: pymongo>=4.7.2; extra == 'all'
Requires-Dist: redis[hiredis]>=5.2.1; extra == 'all'
Requires-Dist: sqlalchemy[asyncio]>=2.0.36; extra == 'all'
Provides-Extra: dynamo
Requires-Dist: aioboto3>=13.3.0; extra == 'dynamo'
Requires-Dist: boto3>=1.35.3; extra == 'dynamo'
Provides-Extra: mongo
Requires-Dist: pymongo>=4.7.2; extra == 'mongo'
Provides-Extra: redis
Requires-Dist: redis[hiredis]>=5.2.1; extra == 'redis'
Provides-Extra: sqlalchemy
Requires-Dist: aioodbc>=0.5.0; extra == 'sqlalchemy'
Requires-Dist: aiosqlite>=0.20.0; extra == 'sqlalchemy'
Requires-Dist: asyncpg>=0.30.0; extra == 'sqlalchemy'
Requires-Dist: sqlalchemy[asyncio]>=2.0.36; extra == 'sqlalchemy'
